{
  "slug": "skincare-between-facials",
  "schemaVersion": 1,
  "settings": {
    "title": "What to Actually Do for Your Skin Between Facials",
    "date": "2026-02-15",
    "excerpt": "A whole shelf of products is rarely the answer, and one habit beats all of them.",
    "body": "<p>Clients ask us constantly which products they should be buying. Honestly, the routine matters far more than the shelf.</p><p><strong>Wear sunscreen every day.</strong> Nothing else you do will protect your skin as much, even in winter, even indoors by a window.</p><p><strong>Do less, not more.</strong> A gentle cleanser and a good moisturizer beat a ten-step routine that leaves skin irritated.</p><p>Drink water and sleep when you can. It is dull advice, but your skin shows both faster than anything in a bottle.</p>"
  }
}
