{
  "name": "Menu",
  "slug": "menu",
  "id": "menu",
  "created": "2026-04-14T10:00:00.000Z",
  "updated": "2026-04-14T10:00:00.000Z",
  "widgets": {
    "menu_intro": {
      "type": "banner",
      "settings": {
        "fullwidth": true,
        "height": "small",
        "content_width": "medium",
        "alignment": "center",
        "vertical_alignment": "center",
        "color_scheme": "standard-primary",
        "top_spacing": "auto",
        "bottom_spacing": "auto"
      },
      "blocks": {
        "eyebrow": {
          "type": "text",
          "settings": {
            "text": "<p>The menu</p>",
            "size": "sm",
            "uppercase": true,
            "muted": true
          }
        },
        "title": {
          "type": "heading",
          "settings": {
            "text": "This week at Saffron",
            "size": "5xl"
          }
        },
        "subtitle": {
          "type": "text",
          "settings": {
            "text": "<p>Updated every Tuesday. Available à la carte or as a four-course tasting.</p>",
            "size": "base",
            "uppercase": false,
            "muted": false
          }
        }
      },
      "blocksOrder": ["eyebrow", "title", "subtitle"]
    },
    "menu_starters": {
      "type": "priced-list",
      "settings": {
        "eyebrow": "Starters",
        "eyebrow_uppercase": true,
        "heading_alignment": "start",
        "layout": "single-column",
        "color_scheme": "standard-primary",
        "top_spacing": "auto",
        "bottom_spacing": "auto"
      },
      "blocks": {
        "s-1": {
          "type": "item",
          "settings": {
            "name": "Warm focaccia, cultured butter",
            "description": "<p>sea salt, fresh rosemary</p>",
            "price": "8"
          }
        },
        "s-2": {
          "type": "item",
          "settings": {
            "name": "Heirloom tomato, burrata",
            "description": "<p>basil oil, toasted sourdough</p>",
            "price": "16"
          }
        },
        "s-3": {
          "type": "item",
          "settings": {
            "name": "Grilled octopus",
            "description": "<p>white bean, chili, smoked paprika</p>",
            "price": "18"
          }
        },
        "s-4": {
          "type": "item",
          "settings": {
            "name": "Beet tartare",
            "description": "<p>horseradish crème, rye crisp, dill</p>",
            "price": "15"
          }
        },
        "s-5": {
          "type": "item",
          "settings": {
            "name": "Roasted bone marrow",
            "description": "<p>caper gremolata, grilled bread</p>",
            "price": "19"
          }
        }
      },
      "blocksOrder": ["s-1", "s-2", "s-3", "s-4", "s-5"]
    },
    "menu_mains": {
      "type": "priced-list",
      "settings": {
        "eyebrow": "Mains",
        "eyebrow_uppercase": true,
        "heading_alignment": "start",
        "layout": "single-column",
        "color_scheme": "standard-secondary",
        "top_spacing": "auto",
        "bottom_spacing": "auto"
      },
      "blocks": {
        "m-1": {
          "type": "item",
          "settings": {
            "name": "Hand-cut tagliatelle",
            "description": "<p>brown butter, sage, aged parmesan</p>",
            "price": "24"
          }
        },
        "m-2": {
          "type": "item",
          "settings": {
            "name": "Wild mushroom risotto",
            "description": "<p>grana padano, truffle, soft herbs</p>",
            "price": "28"
          }
        },
        "m-3": {
          "type": "item",
          "settings": {
            "name": "Day-boat halibut",
            "description": "<p>fennel, preserved lemon, new potatoes</p>",
            "price": "36"
          }
        },
        "m-4": {
          "type": "item",
          "settings": {
            "name": "Pan-roasted duck breast",
            "description": "<p>charred radicchio, cherry, balsamic</p>",
            "price": "38"
          }
        },
        "m-5": {
          "type": "item",
          "settings": {
            "name": "Slow-braised short rib",
            "description": "<p>polenta, salsa verde, pickled shallot</p>",
            "price": "34"
          }
        },
        "m-6": {
          "type": "item",
          "settings": {
            "name": "Dry-aged ribeye for two",
            "description": "<p>roasted shallot jus, watercress</p>",
            "price": "88"
          }
        }
      },
      "blocksOrder": ["m-1", "m-2", "m-3", "m-4", "m-5", "m-6"]
    },
    "menu_desserts": {
      "type": "priced-list",
      "settings": {
        "eyebrow": "Desserts",
        "eyebrow_uppercase": true,
        "heading_alignment": "start",
        "layout": "single-column",
        "color_scheme": "standard-primary",
        "top_spacing": "auto",
        "bottom_spacing": "auto"
      },
      "blocks": {
        "d-1": {
          "type": "item",
          "settings": {
            "name": "Olive oil cake, crème fraîche",
            "description": "<p>candied citrus, toasted almond</p>",
            "price": "12"
          }
        },
        "d-2": {
          "type": "item",
          "settings": {
            "name": "Dark chocolate tart",
            "description": "<p>smoked sea salt, espresso cream</p>",
            "price": "13"
          }
        },
        "d-3": {
          "type": "item",
          "settings": {
            "name": "Pear tarte tatin",
            "description": "<p>bay leaf ice cream, caramel</p>",
            "price": "14"
          }
        },
        "d-4": {
          "type": "item",
          "settings": {
            "name": "Selection of cheeses",
            "description": "<p>honeycomb, walnut, seeded crackers</p>",
            "price": "18"
          }
        }
      },
      "blocksOrder": ["d-1", "d-2", "d-3", "d-4"]
    },
    "menu_wine": {
      "type": "priced-list",
      "settings": {
        "eyebrow": "Wine by the glass",
        "eyebrow_uppercase": true,
        "heading_alignment": "start",
        "layout": "two-column",
        "color_scheme": "standard-secondary",
        "top_spacing": "auto",
        "bottom_spacing": "auto"
      },
      "blocks": {
        "w-1": {
          "type": "item",
          "settings": {
            "name": "Pét-nat rosé",
            "description": "<p>Loire, France</p>",
            "price": "14"
          }
        },
        "w-2": {
          "type": "item",
          "settings": {
            "name": "Assyrtiko",
            "description": "<p>Santorini, Greece</p>",
            "price": "16"
          }
        },
        "w-3": {
          "type": "item",
          "settings": {
            "name": "Chablis, estate",
            "description": "<p>Burgundy, France</p>",
            "price": "18"
          }
        },
        "w-4": {
          "type": "item",
          "settings": {
            "name": "Etna Bianco",
            "description": "<p>Sicily, Italy</p>",
            "price": "15"
          }
        },
        "w-5": {
          "type": "item",
          "settings": {
            "name": "Gamay, whole-cluster",
            "description": "<p>Beaujolais, France</p>",
            "price": "14"
          }
        },
        "w-6": {
          "type": "item",
          "settings": {
            "name": "Nebbiolo, Langhe",
            "description": "<p>Piedmont, Italy</p>",
            "price": "19"
          }
        },
        "w-7": {
          "type": "item",
          "settings": {
            "name": "Mencía",
            "description": "<p>Ribeira Sacra, Spain</p>",
            "price": "15"
          }
        },
        "w-8": {
          "type": "item",
          "settings": {
            "name": "Tawny port, 20-year",
            "description": "<p>Douro, Portugal</p>",
            "price": "16"
          }
        }
      },
      "blocksOrder": ["w-1", "w-2", "w-3", "w-4", "w-5", "w-6", "w-7", "w-8"]
    },
    "menu_cta": {
      "type": "action-bar",
      "settings": {
        "fullwidth": false,
        "color_scheme": "highlight-primary",
        "top_spacing": "auto",
        "bottom_spacing": "auto"
      },
      "blocks": {
        "heading": {
          "type": "heading",
          "settings": {
            "text": "Ready to eat?",
            "size": "3xl"
          }
        },
        "text": {
          "type": "text",
          "settings": {
            "text": "<p>Tables turn quickly on weekends — book ahead.</p>",
            "size": "base",
            "uppercase": false,
            "muted": false
          }
        },
        "cta": {
          "type": "button",
          "settings": {
            "link": {
              "href": "reservations.html",
              "text": "Reserve a Table",
              "target": "_self"
            },
            "style": "primary",
            "link_2": {
              "href": "tel:+17185550142",
              "text": "Call (718) 555-0142",
              "target": "_self"
            },
            "style_2": "secondary",
            "size": "large"
          }
        }
      },
      "blocksOrder": ["heading", "text", "cta"]
    }
  },
  "widgetsOrder": ["menu_intro", "menu_starters", "menu_mains", "menu_desserts", "menu_wine", "menu_cta"]
}
