{
  "slug": "spring-equinox-workshop",
  "schemaVersion": 1,
  "settings": {
    "title": "Spring Equinox Morning Workshop",
    "date": "2026-04-11",
    "excerpt": "Mark the turn of the season with a two hour Saturday morning practice followed by tea together.",
    "body": "<p>The equinox is a natural moment to pause and reset, and we are holding a special workshop to mark it. Join us on a Saturday morning for two unhurried hours on the mat.</p><p>The session moves from gentle waking movement into a flowing sequence and ends with a long, deep rest. It is designed to shake off winter heaviness and meet the lighter months with energy.</p><p>Afterwards we will share tea and something to eat in the studio. It is as much about community as it is about the practice.</p><p>Spaces are limited by the size of our room, so please reserve early. All levels are welcome and props are provided.</p>"
  }
}
